proxyscrape/VERSION
proxyscrape/__init__.py
proxyscrape/errors.py
proxyscrape/integration.py
proxyscrape/proxyscrape.py
proxyscrape/scrapers.py
proxyscrape/shared.py
proxyscrape/stores.py
proxyscrape-0.3.0.dist-info/LICENSE.txt
proxyscrape-0.3.0.dist-info/METADATA
proxyscrape-0.3.0.dist-info/RECORD
proxyscrape-0.3.0.dist-info/WHEEL
proxyscrape-0.3.0.dist-info/top_level.txt
